setup.cfg
setup.py
twemredis.py
twemredis.egg-info/PKG-INFO
twemredis.egg-info/SOURCES.txt
twemredis.egg-info/dependency_links.txt
twemredis.egg-info/requires.txt
twemredis.egg-info/top_level.txt