Metadata-Version: 1.1
Name: twemredis
Version: 0.1.0
Summary: Redis wrapper library for using twemproxy sharded Redis
Home-page: https://github.com/mishan/twemredis-py
Author: Misha Nasledov
Author-email: misha@nasledov.com
License: Apache 2.0
Keywords: redis twemproxy nutcracker development
Platform: UNKNOWN
Classifier: Development Status :: 4 - Beta
Classifier: Intended Audience :: Developers
Classifier: License :: OSI Approved :: MIT License
Classifier: Programming Language :: Python :: 2
Classifier: Programming Language :: Python :: 2.6
Classifier: Programming Language :: Python :: 2.7
Classifier: Programming Language :: Python :: 3
Classifier: Programming Language :: Python :: 3.3
Classifier: Programming Language :: Python :: 3.4
Classifier: Programming Language :: Python :: 3.5
